nminer/__init__.py
nminer/scratchpad.py
nminer/viziertest.py
nminer/algs/__init__.py
nminer/algs/base.py
nminer/algs/batch.py
nminer/algs/rl.py
nminer/algs/sample.py
nminer/algs/vizier.py
nminer/cache/__init__.py
nminer/cache/common.py
nminer/cache/dynamic.py
nminer/cache/multi.py
nminer/cache/proactive.py
nminer/cache/static.py
nminer/eval/__init__.py
nminer/eval/bench.py
nminer/eval/gen.py
nminer/eval/post_batch.py
nminer/eval/run_batch.py
nminer/eval/run_single.py
nminer/interface/__init__.py
nminer/interface/example.py
nminer/interface/gui.py
nminer/interface/mine.py
nminer/sql/__init__.py
nminer/sql/cost.py
nminer/sql/pred.py
nminer/sql/query.py
nminer/stats/__init__.py
nminer/stats/amt_custom.py
nminer/stats/amt_survey.py
nminer/stats/batches.py
nminer/stats/common.py
nminer/stats/items.py
nminer/stats/survey.py
nminer/text/__init__.py
nminer/text/fact.py
nminer/text/sum.py
naturalminer-0.1.0.dist-info/LICENSE
naturalminer-0.1.0.dist-info/METADATA
naturalminer-0.1.0.dist-info/WHEEL
naturalminer-0.1.0.dist-info/top_level.txt
naturalminer-0.1.0.dist-info/RECORD
